{
    "type": "FeatureCollection",
    "properties": {
        "name": "Quercus pachyloma"
    },
    "features": [
        {
            "type": "Feature",
            "geometry": {
                "type": "Point",
                "coordinates": [
                    120.835,
                    22.243333
                ]
            },
            "properties": {
                "type": "occurrence",
                "record": "<a href=https://www.gbif.org/occurrence/1822088223 target='_blank'>https://www.gbif.org/occurrence/1822088223</a>",
                "outlier": "false"
            }
        },
        {
            "type": "Feature",
            "geometry": {
                "type": "Point",
                "coordinates": [
                    120.8425,
                    22.320639
                ]
            },
            "properties": {
                "type": "occurrence",
                "record": "<a href=https://www.gbif.org/occurrence/2825620233 target='_blank'>https://www.gbif.org/occurrence/2825620233</a>",
                "outlier": "false"
            }
        },
        {
            "type": "Feature",
            "geometry": {
                "type": "Point",
                "coordinates": [
                    120.8425,
                    22.320639
                ]
            },
            "properties": {
                "type": "occurrence",
                "record": "<a href=https://www.gbif.org/occurrence/2825620234 target='_blank'>https://www.gbif.org/occurrence/2825620234</a>",
                "outlier": "false"
            }
        },
        {
            "type": "Feature",
            "geometry": {
                "type": "Point",
                "coordinates": [
                    120.8425,
                    22.320639
                ]
            },
            "properties": {
                "type": "occurrence",
                "record": "<a href=https://www.gbif.org/occurrence/2825621260 target='_blank'>https://www.gbif.org/occurrence/2825621260</a>",
                "outlier": "false"
            }
        },
        {
            "type": "Feature",
            "geometry": {
                "type": "Point",
                "coordinates": [
                    120.8425,
                    22.320639
                ]
            },
            "properties": {
                "type": "occurrence",
                "record": "<a href=https://www.gbif.org/occurrence/2825622206 target='_blank'>https://www.gbif.org/occurrence/2825622206</a>",
                "outlier": "false"
            }
        },
        {
            "type": "Feature",
            "geometry": {
                "type": "Point",
                "coordinates": [
                    120.8425,
                    22.320639
                ]
            },
            "properties": {
                "type": "occurrence",
                "record": "<a href=https://www.gbif.org/occurrence/2825623124 target='_blank'>https://www.gbif.org/occurrence/2825623124</a>",
                "outlier": "false"
            }
        },
        {
            "type": "Feature",
            "geometry": {
                "type": "Point",
                "coordinates": [
                    120.8425,
                    22.320639
                ]
            },
            "properties": {
                "type": "occurrence",
                "record": "<a href=https://www.gbif.org/occurrence/2825624298 target='_blank'>https://www.gbif.org/occurrence/2825624298</a>",
                "outlier": "false"
            }
        },
        {
            "type": "Feature",
            "geometry": {
                "type": "Point",
                "coordinates": [
                    120.8425,
                    22.320639
                ]
            },
            "properties": {
                "type": "occurrence",
                "record": "<a href=https://www.gbif.org/occurrence/2825627254 target='_blank'>https://www.gbif.org/occurrence/2825627254</a>",
                "outlier": "false"
            }
        },
        {
            "type": "Feature",
            "geometry": {
                "type": "Point",
                "coordinates": [
                    120.8425,
                    22.320639
                ]
            },
            "properties": {
                "type": "occurrence",
                "record": "<a href=https://www.gbif.org/occurrence/2825629247 target='_blank'>https://www.gbif.org/occurrence/2825629247</a>",
                "outlier": "false"
            }
        },
        {
            "type": "Feature",
            "geometry": {
                "type": "Point",
                "coordinates": [
                    120.8425,
                    22.320639
                ]
            },
            "properties": {
                "type": "occurrence",
                "record": "<a href=https://www.gbif.org/occurrence/2825650223 target='_blank'>https://www.gbif.org/occurrence/2825650223</a>",
                "outlier": "false"
            }
        },
        {
            "type": "Feature",
            "geometry": {
                "type": "Point",
                "coordinates": [
                    120.8425,
                    22.320639
                ]
            },
            "properties": {
                "type": "occurrence",
                "record": "<a href=https://www.gbif.org/occurrence/2825653252 target='_blank'>https://www.gbif.org/occurrence/2825653252</a>",
                "outlier": "false"
            }
        },
        {
            "type": "Feature",
            "geometry": {
                "type": "Point",
                "coordinates": [
                    120.8425,
                    22.320639
                ]
            },
            "properties": {
                "type": "occurrence",
                "record": "<a href=https://www.gbif.org/occurrence/2825653253 target='_blank'>https://www.gbif.org/occurrence/2825653253</a>",
                "outlier": "false"
            }
        },
        {
            "type": "Feature",
            "geometry": {
                "type": "Point",
                "coordinates": [
                    120.8425,
                    22.320639
                ]
            },
            "properties": {
                "type": "occurrence",
                "record": "<a href=https://www.gbif.org/occurrence/2825654259 target='_blank'>https://www.gbif.org/occurrence/2825654259</a>",
                "outlier": "false"
            }
        },
        {
            "type": "Feature",
            "geometry": {
                "type": "Point",
                "coordinates": [
                    120.8425,
                    22.320639
                ]
            },
            "properties": {
                "type": "occurrence",
                "record": "<a href=https://www.gbif.org/occurrence/2825654261 target='_blank'>https://www.gbif.org/occurrence/2825654261</a>",
                "outlier": "false"
            }
        },
        {
            "type": "Feature",
            "geometry": {
                "type": "Point",
                "coordinates": [
                    120.8425,
                    22.320639
                ]
            },
            "properties": {
                "type": "occurrence",
                "record": "<a href=https://www.gbif.org/occurrence/2825655128 target='_blank'>https://www.gbif.org/occurrence/2825655128</a>",
                "outlier": "false"
            }
        },
        {
            "type": "Feature",
            "geometry": {
                "type": "Point",
                "coordinates": [
                    120.8425,
                    22.320639
                ]
            },
            "properties": {
                "type": "occurrence",
                "record": "<a href=https://www.gbif.org/occurrence/2825656279 target='_blank'>https://www.gbif.org/occurrence/2825656279</a>",
                "outlier": "false"
            }
        },
        {
            "type": "Feature",
            "geometry": {
                "type": "Point",
                "coordinates": [
                    120.8425,
                    22.320639
                ]
            },
            "properties": {
                "type": "occurrence",
                "record": "<a href=https://www.gbif.org/occurrence/2825656280 target='_blank'>https://www.gbif.org/occurrence/2825656280</a>",
                "outlier": "false"
            }
        },
        {
            "type": "Feature",
            "geometry": {
                "type": "Point",
                "coordinates": [
                    120.8425,
                    22.320639
                ]
            },
            "properties": {
                "type": "occurrence",
                "record": "<a href=https://www.gbif.org/occurrence/2825656281 target='_blank'>https://www.gbif.org/occurrence/2825656281</a>",
                "outlier": "false"
            }
        },
        {
            "type": "Feature",
            "geometry": {
                "type": "Point",
                "coordinates": [
                    120.8425,
                    22.320639
                ]
            },
            "properties": {
                "type": "occurrence",
                "record": "<a href=https://www.gbif.org/occurrence/2825657212 target='_blank'>https://www.gbif.org/occurrence/2825657212</a>",
                "outlier": "false"
            }
        },
        {
            "type": "Feature",
            "geometry": {
                "type": "Point",
                "coordinates": [
                    120.8425,
                    22.320639
                ]
            },
            "properties": {
                "type": "occurrence",
                "record": "<a href=https://www.gbif.org/occurrence/2825657213 target='_blank'>https://www.gbif.org/occurrence/2825657213</a>",
                "outlier": "false"
            }
        },
        {
            "type": "Feature",
            "geometry": {
                "type": "Point",
                "coordinates": [
                    120.8425,
                    22.320639
                ]
            },
            "properties": {
                "type": "occurrence",
                "record": "<a href=https://www.gbif.org/occurrence/2825658252 target='_blank'>https://www.gbif.org/occurrence/2825658252</a>",
                "outlier": "false"
            }
        },
        {
            "type": "Feature",
            "geometry": {
                "type": "Point",
                "coordinates": [
                    120.8425,
                    22.320639
                ]
            },
            "properties": {
                "type": "occurrence",
                "record": "<a href=https://www.gbif.org/occurrence/2825659222 target='_blank'>https://www.gbif.org/occurrence/2825659222</a>",
                "outlier": "false"
            }
        },
        {
            "type": "Feature",
            "geometry": {
                "type": "Point",
                "coordinates": [
                    120.8425,
                    22.320639
                ]
            },
            "properties": {
                "type": "occurrence",
                "record": "<a href=https://www.gbif.org/occurrence/2825659223 target='_blank'>https://www.gbif.org/occurrence/2825659223</a>",
                "outlier": "false"
            }
        },
        {
            "type": "Feature",
            "geometry": {
                "type": "Point",
                "coordinates": [
                    120.883333,
                    23.916667
                ]
            },
            "properties": {
                "type": "occurrence",
                "record": "<a href=https://www.gbif.org/occurrence/1821888811 target='_blank'>https://www.gbif.org/occurrence/1821888811</a>",
                "outlier": "false"
            }
        },
        {
            "type": "Feature",
            "geometry": {
                "type": "Point",
                "coordinates": [
                    120.95,
                    24.15
                ]
            },
            "properties": {
                "type": "occurrence",
                "record": "<a href=https://www.gbif.org/occurrence/1821783281 target='_blank'>https://www.gbif.org/occurrence/1821783281</a>",
                "outlier": "false"
            }
        },
        {
            "type": "Feature",
            "geometry": {
                "type": "Point",
                "coordinates": [
                    121.604167,
                    24.768056
                ]
            },
            "properties": {
                "type": "occurrence",
                "record": "<a href=https://www.gbif.org/occurrence/1821811994 target='_blank'>https://www.gbif.org/occurrence/1821811994</a>",
                "outlier": "false"
            }
        },
        {
            "type": "Feature",
            "geometry": {
                "type": "Point",
                "coordinates": [
                    121.604167,
                    24.768056
                ]
            },
            "properties": {
                "type": "occurrence",
                "record": "<a href=https://www.gbif.org/occurrence/1821812301 target='_blank'>https://www.gbif.org/occurrence/1821812301</a>",
                "outlier": "false"
            }
        },
        {
            "type": "Feature",
            "geometry": {
                "type": "Point",
                "coordinates": [
                    120.98,
                    23.83
                ]
            },
            "properties": {
                "type": "occurrence",
                "record": "<a href=https://www.gbif.org/occurrence/2417371655 target='_blank'>https://www.gbif.org/occurrence/2417371655</a>",
                "outlier": "false"
            }
        },
        {
            "type": "Feature",
            "geometry": {
                "type": "Point",
                "coordinates": [
                    120.833333,
                    22.116667
                ]
            },
            "properties": {
                "type": "occurrence",
                "record": "<a href=https://www.gbif.org/occurrence/1821810057 target='_blank'>https://www.gbif.org/occurrence/1821810057</a>",
                "outlier": "false"
            }
        },
        {
            "type": "Feature",
            "geometry": {
                "type": "Point",
                "coordinates": [
                    120.826389,
                    22.1275
                ]
            },
            "properties": {
                "type": "occurrence",
                "record": "<a href=https://www.gbif.org/occurrence/1821952969 target='_blank'>https://www.gbif.org/occurrence/1821952969</a>",
                "outlier": "false"
            }
        },
        {
            "type": "Feature",
            "geometry": {
                "type": "Point",
                "coordinates": [
                    120.833333,
                    22.033333
                ]
            },
            "properties": {
                "type": "occurrence",
                "record": "<a href=https://www.gbif.org/occurrence/1822028746 target='_blank'>https://www.gbif.org/occurrence/1822028746</a>",
                "outlier": "false"
            }
        },
        {
            "type": "Feature",
            "geometry": {
                "type": "Point",
                "coordinates": [
                    120.46,
                    22.65
                ]
            },
            "properties": {
                "type": "occurrence",
                "record": "<a href=https://www.gbif.org/occurrence/2417505471 target='_blank'>https://www.gbif.org/occurrence/2417505471</a>",
                "outlier": "false"
            }
        },
        {
            "type": "Feature",
            "geometry": {
                "type": "Point",
                "coordinates": [
                    120.833333,
                    22.033333
                ]
            },
            "properties": {
                "type": "occurrence",
                "record": "<a href=https://www.gbif.org/occurrence/1821805279 target='_blank'>https://www.gbif.org/occurrence/1821805279</a>",
                "outlier": "false"
            }
        },
        {
            "type": "Feature",
            "geometry": {
                "type": "Point",
                "coordinates": [
                    120.844444,
                    22.077778
                ]
            },
            "properties": {
                "type": "occurrence",
                "record": "<a href=https://www.gbif.org/occurrence/1821802285 target='_blank'>https://www.gbif.org/occurrence/1821802285</a>",
                "outlier": "false"
            }
        },
        {
            "type": "Feature",
            "geometry": {
                "type": "Point",
                "coordinates": [
                    120.844444,
                    22.077778
                ]
            },
            "properties": {
                "type": "occurrence",
                "record": "<a href=https://www.gbif.org/occurrence/1821802441 target='_blank'>https://www.gbif.org/occurrence/1821802441</a>",
                "outlier": "false"
            }
        },
        {
            "type": "Feature",
            "geometry": {
                "type": "Point",
                "coordinates": [
                    120.844444,
                    22.077778
                ]
            },
            "properties": {
                "type": "occurrence",
                "record": "<a href=https://www.gbif.org/occurrence/1821802499 target='_blank'>https://www.gbif.org/occurrence/1821802499</a>",
                "outlier": "false"
            }
        },
        {
            "type": "Feature",
            "geometry": {
                "type": "Point",
                "coordinates": [
                    120.844444,
                    22.077778
                ]
            },
            "properties": {
                "type": "occurrence",
                "record": "<a href=https://www.gbif.org/occurrence/1821802683 target='_blank'>https://www.gbif.org/occurrence/1821802683</a>",
                "outlier": "false"
            }
        },
        {
            "type": "Feature",
            "geometry": {
                "type": "Point",
                "coordinates": [
                    120.866667,
                    23.916667
                ]
            },
            "properties": {
                "type": "occurrence",
                "record": "<a href=https://www.gbif.org/occurrence/1821804095 target='_blank'>https://www.gbif.org/occurrence/1821804095</a>",
                "outlier": "false"
            }
        },
        {
            "type": "Feature",
            "geometry": {
                "type": "Point",
                "coordinates": [
                    120.829444,
                    22.179444
                ]
            },
            "properties": {
                "type": "occurrence",
                "record": "<a href=https://www.gbif.org/occurrence/1821814530 target='_blank'>https://www.gbif.org/occurrence/1821814530</a>",
                "outlier": "false"
            }
        },
        {
            "type": "Feature",
            "geometry": {
                "type": "Point",
                "coordinates": [
                    120.833333,
                    22.25
                ]
            },
            "properties": {
                "type": "occurrence",
                "record": "<a href=https://www.gbif.org/occurrence/1821806456 target='_blank'>https://www.gbif.org/occurrence/1821806456</a>",
                "outlier": "false"
            }
        },
        {
            "type": "Feature",
            "geometry": {
                "type": "Point",
                "coordinates": [
                    120.866667,
                    23.916667
                ]
            },
            "properties": {
                "type": "occurrence",
                "record": "<a href=https://www.gbif.org/occurrence/1821800844 target='_blank'>https://www.gbif.org/occurrence/1821800844</a>",
                "outlier": "false"
            }
        },
        {
            "type": "Feature",
            "geometry": {
                "type": "Point",
                "coordinates": [
                    120.866667,
                    23.916667
                ]
            },
            "properties": {
                "type": "occurrence",
                "record": "<a href=https://www.gbif.org/occurrence/1821802328 target='_blank'>https://www.gbif.org/occurrence/1821802328</a>",
                "outlier": "false"
            }
        },
        {
            "type": "Feature",
            "geometry": {
                "type": "Point",
                "coordinates": [
                    120.98,
                    23.83
                ]
            },
            "properties": {
                "type": "occurrence",
                "record": "<a href=https://www.gbif.org/occurrence/2417373430 target='_blank'>https://www.gbif.org/occurrence/2417373430</a>",
                "outlier": "false"
            }
        },
        {
            "type": "Feature",
            "geometry": {
                "type": "Point",
                "coordinates": [
                    120.833333,
                    22.25
                ]
            },
            "properties": {
                "type": "occurrence",
                "record": "<a href=https://www.gbif.org/occurrence/1821840893 target='_blank'>https://www.gbif.org/occurrence/1821840893</a>",
                "outlier": "false"
            }
        },
        {
            "type": "Feature",
            "geometry": {
                "type": "Point",
                "coordinates": [
                    120.85,
                    22.083333
                ]
            },
            "properties": {
                "type": "occurrence",
                "record": "<a href=https://www.gbif.org/occurrence/1821843682 target='_blank'>https://www.gbif.org/occurrence/1821843682</a>",
                "outlier": "false"
            }
        },
        {
            "type": "Feature",
            "geometry": {
                "type": "Point",
                "coordinates": [
                    120.833333,
                    22.033333
                ]
            },
            "properties": {
                "type": "occurrence",
                "record": "<a href=https://www.gbif.org/occurrence/1821839174 target='_blank'>https://www.gbif.org/occurrence/1821839174</a>",
                "outlier": "false"
            }
        },
        {
            "type": "Feature",
            "geometry": {
                "type": "Point",
                "coordinates": [
                    120.866667,
                    23.916667
                ]
            },
            "properties": {
                "type": "occurrence",
                "record": "<a href=https://www.gbif.org/occurrence/1821800870 target='_blank'>https://www.gbif.org/occurrence/1821800870</a>",
                "outlier": "false"
            }
        },
        {
            "type": "Feature",
            "geometry": {
                "type": "Point",
                "coordinates": [
                    120.866667,
                    23.916667
                ]
            },
            "properties": {
                "type": "occurrence",
                "record": "<a href=https://www.gbif.org/occurrence/1821800895 target='_blank'>https://www.gbif.org/occurrence/1821800895</a>",
                "outlier": "false"
            }
        },
        {
            "type": "Feature",
            "geometry": {
                "type": "Point",
                "coordinates": [
                    120.862778,
                    22.089722
                ]
            },
            "properties": {
                "type": "occurrence",
                "record": "<a href=https://www.gbif.org/occurrence/891596856 target='_blank'>https://www.gbif.org/occurrence/891596856</a>",
                "outlier": "false"
            }
        },
        {
            "type": "Feature",
            "geometry": {
                "type": "Point",
                "coordinates": [
                    120.816667,
                    22.983333
                ]
            },
            "properties": {
                "type": "occurrence",
                "record": "<a href=https://www.gbif.org/occurrence/1821802584 target='_blank'>https://www.gbif.org/occurrence/1821802584</a>",
                "outlier": "false"
            }
        },
        {
            "type": "Feature",
            "geometry": {
                "type": "Point",
                "coordinates": [
                    120.833333,
                    22.25
                ]
            },
            "properties": {
                "type": "occurrence",
                "record": "<a href=https://www.gbif.org/occurrence/1821831458 target='_blank'>https://www.gbif.org/occurrence/1821831458</a>",
                "outlier": "false"
            }
        },
        {
            "type": "Feature",
            "geometry": {
                "type": "Point",
                "coordinates": [
                    120.833333,
                    22.25
                ]
            },
            "properties": {
                "type": "occurrence",
                "record": "<a href=https://www.gbif.org/occurrence/1821881676 target='_blank'>https://www.gbif.org/occurrence/1821881676</a>",
                "outlier": "false"
            }
        },
        {
            "type": "Feature",
            "geometry": {
                "type": "Point",
                "coordinates": [
                    105.055261,
                    24.046484
                ]
            },
            "properties": {
                "type": "occurrence",
                "record": "<a href=https://www.gbif.org/occurrence/919553332 target='_blank'>https://www.gbif.org/occurrence/919553332</a>",
                "outlier": "false"
            }
        },
        {
            "type": "Feature",
            "geometry": {
                "type": "Point",
                "coordinates": [
                    120.834167,
                    22.0725
                ]
            },
            "properties": {
                "type": "occurrence",
                "record": "<a href=https://www.gbif.org/occurrence/891596792 target='_blank'>https://www.gbif.org/occurrence/891596792</a>",
                "outlier": "false"
            }
        },
        {
            "type": "Feature",
            "geometry": {
                "type": "Point",
                "coordinates": [
                    120.833333,
                    22.25
                ]
            },
            "properties": {
                "type": "occurrence",
                "record": "<a href=https://www.gbif.org/occurrence/1821819475 target='_blank'>https://www.gbif.org/occurrence/1821819475</a>",
                "outlier": "false"
            }
        },
        {
            "type": "Feature",
            "geometry": {
                "type": "Point",
                "coordinates": [
                    120.833333,
                    22.25
                ]
            },
            "properties": {
                "type": "occurrence",
                "record": "<a href=https://www.gbif.org/occurrence/1821859217 target='_blank'>https://www.gbif.org/occurrence/1821859217</a>",
                "outlier": "false"
            }
        },
        {
            "type": "Feature",
            "geometry": {
                "type": "Point",
                "coordinates": [
                    120.862778,
                    22.089722
                ]
            },
            "properties": {
                "type": "occurrence",
                "record": "<a href=https://www.gbif.org/occurrence/891600607 target='_blank'>https://www.gbif.org/occurrence/891600607</a>",
                "outlier": "false"
            }
        },
        {
            "type": "Feature",
            "geometry": {
                "type": "Point",
                "coordinates": [
                    120.862778,
                    22.089722
                ]
            },
            "properties": {
                "type": "occurrence",
                "record": "<a href=https://www.gbif.org/occurrence/891599182 target='_blank'>https://www.gbif.org/occurrence/891599182</a>",
                "outlier": "false"
            }
        },
        {
            "type": "Feature",
            "geometry": {
                "type": "Point",
                "coordinates": [
                    120.98,
                    23.83
                ]
            },
            "properties": {
                "type": "occurrence",
                "record": "<a href=https://www.gbif.org/occurrence/2417369233 target='_blank'>https://www.gbif.org/occurrence/2417369233</a>",
                "outlier": "false"
            }
        },
        {
            "type": "Feature",
            "geometry": {
                "type": "Point",
                "coordinates": [
                    117.47,
                    26.72
                ]
            },
            "properties": {
                "type": "occurrence",
                "record": "<a href=https://www.gbif.org/occurrence/2417502095 target='_blank'>https://www.gbif.org/occurrence/2417502095</a>",
                "outlier": "false"
            }
        },
        {
            "type": "Feature",
            "geometry": {
                "type": "Point",
                "coordinates": [
                    120.862778,
                    22.089722
                ]
            },
            "properties": {
                "type": "occurrence",
                "record": "<a href=https://www.gbif.org/occurrence/891589709 target='_blank'>https://www.gbif.org/occurrence/891589709</a>",
                "outlier": "false"
            }
        },
        {
            "type": "Feature",
            "geometry": {
                "type": "Point",
                "coordinates": [
                    120.843611,
                    22.059444
                ]
            },
            "properties": {
                "type": "occurrence",
                "record": "<a href=https://www.gbif.org/occurrence/891605043 target='_blank'>https://www.gbif.org/occurrence/891605043</a>",
                "outlier": "false"
            }
        },
        {
            "type": "Feature",
            "geometry": {
                "type": "Point",
                "coordinates": [
                    120.833333,
                    22.25
                ]
            },
            "properties": {
                "type": "occurrence",
                "record": "<a href=https://www.gbif.org/occurrence/1821805161 target='_blank'>https://www.gbif.org/occurrence/1821805161</a>",
                "outlier": "false"
            }
        },
        {
            "type": "Feature",
            "geometry": {
                "type": "Point",
                "coordinates": [
                    120.833333,
                    22.25
                ]
            },
            "properties": {
                "type": "occurrence",
                "record": "<a href=https://www.gbif.org/occurrence/1821805345 target='_blank'>https://www.gbif.org/occurrence/1821805345</a>",
                "outlier": "false"
            }
        },
        {
            "type": "Feature",
            "geometry": {
                "type": "Point",
                "coordinates": [
                    120.833333,
                    22.25
                ]
            },
            "properties": {
                "type": "occurrence",
                "record": "<a href=https://www.gbif.org/occurrence/1821805397 target='_blank'>https://www.gbif.org/occurrence/1821805397</a>",
                "outlier": "false"
            }
        },
        {
            "type": "Feature",
            "geometry": {
                "type": "Point",
                "coordinates": [
                    120.862778,
                    22.089722
                ]
            },
            "properties": {
                "type": "occurrence",
                "record": "<a href=https://www.gbif.org/occurrence/891601643 target='_blank'>https://www.gbif.org/occurrence/891601643</a>",
                "outlier": "false"
            }
        },
        {
            "type": "Feature",
            "geometry": {
                "type": "Point",
                "coordinates": [
                    114.92,
                    25.38
                ]
            },
            "properties": {
                "type": "occurrence",
                "record": "<a href=https://www.gbif.org/occurrence/2417325634 target='_blank'>https://www.gbif.org/occurrence/2417325634</a>",
                "outlier": "false"
            }
        },
        {
            "type": "Feature",
            "geometry": {
                "type": "Point",
                "coordinates": [
                    114.92,
                    25.38
                ]
            },
            "properties": {
                "type": "occurrence",
                "record": "<a href=https://www.gbif.org/occurrence/2417327665 target='_blank'>https://www.gbif.org/occurrence/2417327665</a>",
                "outlier": "false"
            }
        },
        {
            "type": "Feature",
            "geometry": {
                "type": "Point",
                "coordinates": [
                    120.844444,
                    22.077778
                ]
            },
            "properties": {
                "type": "occurrence",
                "record": "<a href=https://www.gbif.org/occurrence/1821818107 target='_blank'>https://www.gbif.org/occurrence/1821818107</a>",
                "outlier": "false"
            }
        },
        {
            "type": "Feature",
            "geometry": {
                "type": "Point",
                "coordinates": [
                    120.844444,
                    22.077778
                ]
            },
            "properties": {
                "type": "occurrence",
                "record": "<a href=https://www.gbif.org/occurrence/1821818234 target='_blank'>https://www.gbif.org/occurrence/1821818234</a>",
                "outlier": "false"
            }
        },
        {
            "type": "Feature",
            "geometry": {
                "type": "Point",
                "coordinates": [
                    120.844444,
                    22.077778
                ]
            },
            "properties": {
                "type": "occurrence",
                "record": "<a href=https://www.gbif.org/occurrence/1821818261 target='_blank'>https://www.gbif.org/occurrence/1821818261</a>",
                "outlier": "false"
            }
        },
        {
            "type": "Feature",
            "geometry": {
                "type": "Point",
                "coordinates": [
                    120.844444,
                    22.077778
                ]
            },
            "properties": {
                "type": "occurrence",
                "record": "<a href=https://www.gbif.org/occurrence/1821818278 target='_blank'>https://www.gbif.org/occurrence/1821818278</a>",
                "outlier": "false"
            }
        },
        {
            "type": "Feature",
            "geometry": {
                "type": "Point",
                "coordinates": [
                    120.862778,
                    22.089722
                ]
            },
            "properties": {
                "type": "occurrence",
                "record": "<a href=https://www.gbif.org/occurrence/891614328 target='_blank'>https://www.gbif.org/occurrence/891614328</a>",
                "outlier": "false"
            }
        },
        {
            "type": "Feature",
            "geometry": {
                "type": "Point",
                "coordinates": [
                    120.862778,
                    22.089722
                ]
            },
            "properties": {
                "type": "occurrence",
                "record": "<a href=https://www.gbif.org/occurrence/891621287 target='_blank'>https://www.gbif.org/occurrence/891621287</a>",
                "outlier": "false"
            }
        },
        {
            "type": "Feature",
            "geometry": {
                "type": "Point",
                "coordinates": [
                    120.862778,
                    22.089722
                ]
            },
            "properties": {
                "type": "occurrence",
                "record": "<a href=https://www.gbif.org/occurrence/891621657 target='_blank'>https://www.gbif.org/occurrence/891621657</a>",
                "outlier": "false"
            }
        },
        {
            "type": "Feature",
            "geometry": {
                "type": "Point",
                "coordinates": [
                    120.862778,
                    22.089722
                ]
            },
            "properties": {
                "type": "occurrence",
                "record": "<a href=https://www.gbif.org/occurrence/891619092 target='_blank'>https://www.gbif.org/occurrence/891619092</a>",
                "outlier": "false"
            }
        },
        {
            "type": "Feature",
            "geometry": {
                "type": "Point",
                "coordinates": [
                    121.0,
                    24.166667
                ]
            },
            "properties": {
                "type": "occurrence",
                "record": "<a href=https://www.gbif.org/occurrence/1821803242 target='_blank'>https://www.gbif.org/occurrence/1821803242</a>",
                "outlier": "false"
            }
        },
        {
            "type": "Feature",
            "geometry": {
                "type": "Point",
                "coordinates": [
                    121.0,
                    24.166667
                ]
            },
            "properties": {
                "type": "occurrence",
                "record": "<a href=https://www.gbif.org/occurrence/1821810648 target='_blank'>https://www.gbif.org/occurrence/1821810648</a>",
                "outlier": "false"
            }
        },
        {
            "type": "Feature",
            "geometry": {
                "type": "Point",
                "coordinates": [
                    121.0,
                    24.166667
                ]
            },
            "properties": {
                "type": "occurrence",
                "record": "<a href=https://www.gbif.org/occurrence/1821810799 target='_blank'>https://www.gbif.org/occurrence/1821810799</a>",
                "outlier": "false"
            }
        },
        {
            "type": "Feature",
            "geometry": {
                "type": "Point",
                "coordinates": [
                    121.528056,
                    24.489722
                ]
            },
            "properties": {
                "type": "occurrence",
                "record": "<a href=https://www.gbif.org/occurrence/891620801 target='_blank'>https://www.gbif.org/occurrence/891620801</a>",
                "outlier": "false"
            }
        },
        {
            "type": "Feature",
            "geometry": {
                "type": "Point",
                "coordinates": [
                    107.11,
                    22.76
                ]
            },
            "properties": {
                "type": "occurrence",
                "record": "<a href=https://www.gbif.org/occurrence/2417437063 target='_blank'>https://www.gbif.org/occurrence/2417437063</a>",
                "outlier": "false"
            }
        },
        {
            "type": "Feature",
            "geometry": {
                "type": "Point",
                "coordinates": [
                    120.862778,
                    22.089722
                ]
            },
            "properties": {
                "type": "occurrence",
                "record": "<a href=https://www.gbif.org/occurrence/891622478 target='_blank'>https://www.gbif.org/occurrence/891622478</a>",
                "outlier": "false"
            }
        },
        {
            "type": "Feature",
            "geometry": {
                "type": "Point",
                "coordinates": [
                    120.862778,
                    22.089722
                ]
            },
            "properties": {
                "type": "occurrence",
                "record": "<a href=https://www.gbif.org/occurrence/891689974 target='_blank'>https://www.gbif.org/occurrence/891689974</a>",
                "outlier": "false"
            }
        },
        {
            "type": "Feature",
            "geometry": {
                "type": "Point",
                "coordinates": [
                    120.816667,
                    22.983333
                ]
            },
            "properties": {
                "type": "occurrence",
                "record": "<a href=https://www.gbif.org/occurrence/1821811234 target='_blank'>https://www.gbif.org/occurrence/1821811234</a>",
                "outlier": "false"
            }
        },
        {
            "type": "Feature",
            "geometry": {
                "type": "Point",
                "coordinates": [
                    120.816667,
                    22.983333
                ]
            },
            "properties": {
                "type": "occurrence",
                "record": "<a href=https://www.gbif.org/occurrence/1821811685 target='_blank'>https://www.gbif.org/occurrence/1821811685</a>",
                "outlier": "false"
            }
        },
        {
            "type": "Feature",
            "geometry": {
                "type": "Point",
                "coordinates": [
                    118.03,
                    27.75
                ]
            },
            "properties": {
                "type": "occurrence",
                "record": "<a href=https://www.gbif.org/occurrence/2417669943 target='_blank'>https://www.gbif.org/occurrence/2417669943</a>",
                "outlier": "false"
            }
        },
        {
            "type": "Feature",
            "geometry": {
                "type": "Point",
                "coordinates": [
                    118.03,
                    27.75
                ]
            },
            "properties": {
                "type": "occurrence",
                "record": "<a href=https://www.gbif.org/occurrence/2417670151 target='_blank'>https://www.gbif.org/occurrence/2417670151</a>",
                "outlier": "false"
            }
        },
        {
            "type": "Feature",
            "geometry": {
                "type": "Point",
                "coordinates": [
                    118.03,
                    27.75
                ]
            },
            "properties": {
                "type": "occurrence",
                "record": "<a href=https://www.gbif.org/occurrence/2417671138 target='_blank'>https://www.gbif.org/occurrence/2417671138</a>",
                "outlier": "false"
            }
        },
        {
            "type": "Feature",
            "geometry": {
                "type": "Point",
                "coordinates": [
                    120.862778,
                    22.089722
                ]
            },
            "properties": {
                "type": "occurrence",
                "record": "<a href=https://www.gbif.org/occurrence/891633415 target='_blank'>https://www.gbif.org/occurrence/891633415</a>",
                "outlier": "false"
            }
        },
        {
            "type": "Feature",
            "geometry": {
                "type": "Point",
                "coordinates": [
                    120.898056,
                    22.359444
                ]
            },
            "properties": {
                "type": "occurrence",
                "record": "<a href=https://www.gbif.org/occurrence/891633378 target='_blank'>https://www.gbif.org/occurrence/891633378</a>",
                "outlier": "false"
            }
        },
        {
            "type": "Feature",
            "geometry": {
                "type": "Point",
                "coordinates": [
                    120.17,
                    30.27
                ]
            },
            "properties": {
                "type": "occurrence",
                "record": "<a href=https://www.gbif.org/occurrence/2417638852 target='_blank'>https://www.gbif.org/occurrence/2417638852</a>",
                "outlier": "false"
            }
        },
        {
            "type": "Feature",
            "geometry": {
                "type": "Point",
                "coordinates": [
                    120.17,
                    30.27
                ]
            },
            "properties": {
                "type": "occurrence",
                "record": "<a href=https://www.gbif.org/occurrence/2417639675 target='_blank'>https://www.gbif.org/occurrence/2417639675</a>",
                "outlier": "false"
            }
        },
        {
            "type": "Feature",
            "geometry": {
                "type": "Point",
                "coordinates": [
                    103.086573,
                    22.792186
                ]
            },
            "properties": {
                "type": "occurrence",
                "record": "<a href=https://www.gbif.org/occurrence/919553294 target='_blank'>https://www.gbif.org/occurrence/919553294</a>",
                "outlier": "false"
            }
        },
        {
            "type": "Feature",
            "geometry": {
                "type": "Point",
                "coordinates": [
                    120.7,
                    22.0
                ]
            },
            "properties": {
                "type": "occurrence",
                "record": "<a href=https://www.gbif.org/occurrence/2397725396 target='_blank'>https://www.gbif.org/occurrence/2397725396</a>",
                "outlier": "false"
            }
        },
        {
            "type": "Feature",
            "geometry": {
                "type": "Point",
                "coordinates": [
                    120.7,
                    22.0
                ]
            },
            "properties": {
                "type": "occurrence",
                "record": "<a href=https://www.gbif.org/occurrence/2513870036 target='_blank'>https://www.gbif.org/occurrence/2513870036</a>",
                "outlier": "false"
            }
        },
        {
            "type": "Feature",
            "geometry": {
                "type": "Point",
                "coordinates": [
                    110.585686,
                    25.60168
                ]
            },
            "properties": {
                "type": "occurrence",
                "record": "<a href=https://www.gbif.org/occurrence/1030720048 target='_blank'>https://www.gbif.org/occurrence/1030720048</a>",
                "outlier": "false"
            }
        },
        {
            "type": "Feature",
            "geometry": {
                "type": "Point",
                "coordinates": [
                    110.58,
                    25.6
                ]
            },
            "properties": {
                "type": "occurrence",
                "record": "<a href=https://www.gbif.org/occurrence/2417341810 target='_blank'>https://www.gbif.org/occurrence/2417341810</a>",
                "outlier": "false"
            }
        },
        {
            "type": "Feature",
            "geometry": {
                "type": "Point",
                "coordinates": [
                    108.45,
                    26.0
                ]
            },
            "properties": {
                "type": "occurrence",
                "record": "<a href=https://www.gbif.org/occurrence/2417665664 target='_blank'>https://www.gbif.org/occurrence/2417665664</a>",
                "outlier": "false"
            }
        },
        {
            "type": "Feature",
            "geometry": {
                "type": "Point",
                "coordinates": [
                    108.45,
                    26.0
                ]
            },
            "properties": {
                "type": "occurrence",
                "record": "<a href=https://www.gbif.org/occurrence/2417666307 target='_blank'>https://www.gbif.org/occurrence/2417666307</a>",
                "outlier": "false"
            }
        },
        {
            "type": "Feature",
            "geometry": {
                "type": "Point",
                "coordinates": [
                    107.54,
                    25.59
                ]
            },
            "properties": {
                "type": "occurrence",
                "record": "<a href=https://www.gbif.org/occurrence/2417737171 target='_blank'>https://www.gbif.org/occurrence/2417737171</a>",
                "outlier": "false"
            }
        },
        {
            "type": "Feature",
            "geometry": {
                "type": "Point",
                "coordinates": [
                    107.54,
                    25.59
                ]
            },
            "properties": {
                "type": "occurrence",
                "record": "<a href=https://www.gbif.org/occurrence/2417737183 target='_blank'>https://www.gbif.org/occurrence/2417737183</a>",
                "outlier": "false"
            }
        },
        {
            "type": "Feature",
            "geometry": {
                "type": "Point",
                "coordinates": [
                    107.54,
                    25.59
                ]
            },
            "properties": {
                "type": "occurrence",
                "record": "<a href=https://www.gbif.org/occurrence/2417737669 target='_blank'>https://www.gbif.org/occurrence/2417737669</a>",
                "outlier": "false"
            }
        },
        {
            "type": "Feature",
            "geometry": {
                "type": "Point",
                "coordinates": [
                    115.650136,
                    24.95476
                ]
            },
            "properties": {
                "type": "occurrence",
                "record": "<a href=https://www.gbif.org/occurrence/1030746420 target='_blank'>https://www.gbif.org/occurrence/1030746420</a>",
                "outlier": "false"
            }
        },
        {
            "type": "Feature",
            "geometry": {
                "type": "Point",
                "coordinates": [
                    115.650136,
                    24.95476
                ]
            },
            "properties": {
                "type": "occurrence",
                "record": "<a href=https://www.gbif.org/occurrence/1030746433 target='_blank'>https://www.gbif.org/occurrence/1030746433</a>",
                "outlier": "false"
            }
        },
        {
            "type": "Feature",
            "geometry": {
                "type": "Point",
                "coordinates": [
                    115.938699,
                    24.655471
                ]
            },
            "properties": {
                "type": "occurrence",
                "record": "<a href=https://www.gbif.org/occurrence/1030984810 target='_blank'>https://www.gbif.org/occurrence/1030984810</a>",
                "outlier": "false"
            }
        },
        {
            "type": "Feature",
            "geometry": {
                "type": "Point",
                "coordinates": [
                    114.269636,
                    23.376591
                ]
            },
            "properties": {
                "type": "occurrence",
                "record": "<a href=https://www.gbif.org/occurrence/1030984825 target='_blank'>https://www.gbif.org/occurrence/1030984825</a>",
                "outlier": "false"
            }
        },
        {
            "type": "Feature",
            "geometry": {
                "type": "Point",
                "coordinates": [
                    114.176992,
                    24.079566
                ]
            },
            "properties": {
                "type": "occurrence",
                "record": "<a href=https://www.gbif.org/occurrence/1030984834 target='_blank'>https://www.gbif.org/occurrence/1030984834</a>",
                "outlier": "false"
            }
        },
        {
            "type": "Feature",
            "geometry": {
                "type": "Point",
                "coordinates": [
                    114.26,
                    23.37
                ]
            },
            "properties": {
                "type": "occurrence",
                "record": "<a href=https://www.gbif.org/occurrence/2417377594 target='_blank'>https://www.gbif.org/occurrence/2417377594</a>",
                "outlier": "false"
            }
        },
        {
            "type": "Feature",
            "geometry": {
                "type": "Point",
                "coordinates": [
                    115.39,
                    25.13
                ]
            },
            "properties": {
                "type": "occurrence",
                "record": "<a href=https://www.gbif.org/occurrence/2417476694 target='_blank'>https://www.gbif.org/occurrence/2417476694</a>",
                "outlier": "false"
            }
        },
        {
            "type": "Feature",
            "geometry": {
                "type": "Point",
                "coordinates": [
                    115.65,
                    24.95
                ]
            },
            "properties": {
                "type": "occurrence",
                "record": "<a href=https://www.gbif.org/occurrence/2417497650 target='_blank'>https://www.gbif.org/occurrence/2417497650</a>",
                "outlier": "false"
            }
        },
        {
            "type": "Feature",
            "geometry": {
                "type": "Point",
                "coordinates": [
                    115.65,
                    24.95
                ]
            },
            "properties": {
                "type": "occurrence",
                "record": "<a href=https://www.gbif.org/occurrence/2417498532 target='_blank'>https://www.gbif.org/occurrence/2417498532</a>",
                "outlier": "false"
            }
        },
        {
            "type": "Feature",
            "geometry": {
                "type": "Point",
                "coordinates": [
                    115.93,
                    24.65
                ]
            },
            "properties": {
                "type": "occurrence",
                "record": "<a href=https://www.gbif.org/occurrence/2417556379 target='_blank'>https://www.gbif.org/occurrence/2417556379</a>",
                "outlier": "false"
            }
        },
        {
            "type": "Feature",
            "geometry": {
                "type": "Point",
                "coordinates": [
                    118.03,
                    27.75
                ]
            },
            "properties": {
                "type": "occurrence",
                "record": "<a href=https://www.gbif.org/occurrence/2417669434 target='_blank'>https://www.gbif.org/occurrence/2417669434</a>",
                "outlier": "false"
            }
        },
        {
            "type": "Feature",
            "geometry": {
                "type": "Point",
                "coordinates": [
                    118.03,
                    27.75
                ]
            },
            "properties": {
                "type": "occurrence",
                "record": "<a href=https://www.gbif.org/occurrence/2417670327 target='_blank'>https://www.gbif.org/occurrence/2417670327</a>",
                "outlier": "false"
            }
        },
        {
            "type": "Feature",
            "geometry": {
                "type": "Point",
                "coordinates": [
                    118.03,
                    27.75
                ]
            },
            "properties": {
                "type": "occurrence",
                "record": "<a href=https://www.gbif.org/occurrence/2417670383 target='_blank'>https://www.gbif.org/occurrence/2417670383</a>",
                "outlier": "false"
            }
        },
        {
            "type": "Feature",
            "geometry": {
                "type": "Point",
                "coordinates": [
                    118.03,
                    27.75
                ]
            },
            "properties": {
                "type": "occurrence",
                "record": "<a href=https://www.gbif.org/occurrence/2417671118 target='_blank'>https://www.gbif.org/occurrence/2417671118</a>",
                "outlier": "false"
            }
        },
        {
            "type": "Feature",
            "geometry": {
                "type": "Point",
                "coordinates": [
                    118.03,
                    27.75
                ]
            },
            "properties": {
                "type": "occurrence",
                "record": "<a href=https://www.gbif.org/occurrence/2417671190 target='_blank'>https://www.gbif.org/occurrence/2417671190</a>",
                "outlier": "false"
            }
        },
        {
            "type": "Feature",
            "geometry": {
                "type": "Point",
                "coordinates": [
                    120.866667,
                    23.916667
                ]
            },
            "properties": {
                "type": "occurrence",
                "record": "<a href=https://www.gbif.org/occurrence/1821800527 target='_blank'>https://www.gbif.org/occurrence/1821800527</a>",
                "outlier": "false"
            }
        },
        {
            "type": "Feature",
            "geometry": {
                "type": "Point",
                "coordinates": [
                    120.844444,
                    22.077778
                ]
            },
            "properties": {
                "type": "occurrence",
                "record": "<a href=https://www.gbif.org/occurrence/1821800600 target='_blank'>https://www.gbif.org/occurrence/1821800600</a>",
                "outlier": "false"
            }
        },
        {
            "type": "Feature",
            "geometry": {
                "type": "Point",
                "coordinates": [
                    110.040006,
                    25.742153
                ]
            },
            "properties": {
                "type": "occurrence",
                "record": "<a href=https://www.gbif.org/occurrence/1030720073 target='_blank'>https://www.gbif.org/occurrence/1030720073</a>",
                "outlier": "false"
            }
        },
        {
            "type": "Feature",
            "geometry": {
                "type": "Point",
                "coordinates": [
                    110.040007,
                    25.742153
                ]
            },
            "properties": {
                "type": "occurrence",
                "record": "<a href=https://www.gbif.org/occurrence/1030984832 target='_blank'>https://www.gbif.org/occurrence/1030984832</a>",
                "outlier": "false"
            }
        },
        {
            "type": "Feature",
            "geometry": {
                "type": "Point",
                "coordinates": [
                    110.040007,
                    25.742153
                ]
            },
            "properties": {
                "type": "occurrence",
                "record": "<a href=https://www.gbif.org/occurrence/1030984847 target='_blank'>https://www.gbif.org/occurrence/1030984847</a>",
                "outlier": "false"
            }
        },
        {
            "type": "Feature",
            "geometry": {
                "type": "Point",
                "coordinates": [
                    110.040007,
                    25.742153
                ]
            },
            "properties": {
                "type": "occurrence",
                "record": "<a href=https://www.gbif.org/occurrence/1030984853 target='_blank'>https://www.gbif.org/occurrence/1030984853</a>",
                "outlier": "false"
            }
        },
        {
            "type": "Feature",
            "geometry": {
                "type": "Point",
                "coordinates": [
                    110.352269,
                    24.547767
                ]
            },
            "properties": {
                "type": "occurrence",
                "record": "<a href=https://www.gbif.org/occurrence/1030984864 target='_blank'>https://www.gbif.org/occurrence/1030984864</a>",
                "outlier": "false"
            }
        },
        {
            "type": "Feature",
            "geometry": {
                "type": "Point",
                "coordinates": [
                    110.352269,
                    24.547767
                ]
            },
            "properties": {
                "type": "occurrence",
                "record": "<a href=https://www.gbif.org/occurrence/1030984866 target='_blank'>https://www.gbif.org/occurrence/1030984866</a>",
                "outlier": "false"
            }
        },
        {
            "type": "Feature",
            "geometry": {
                "type": "Point",
                "coordinates": [
                    116.625881,
                    24.33566
                ]
            },
            "properties": {
                "type": "occurrence",
                "record": "<a href=https://www.gbif.org/occurrence/1030984869 target='_blank'>https://www.gbif.org/occurrence/1030984869</a>",
                "outlier": "false"
            }
        },
        {
            "type": "Feature",
            "geometry": {
                "type": "Point",
                "coordinates": [
                    113.18,
                    24.81
                ]
            },
            "properties": {
                "type": "occurrence",
                "record": "<a href=https://www.gbif.org/occurrence/2417303492 target='_blank'>https://www.gbif.org/occurrence/2417303492</a>",
                "outlier": "false"
            }
        },
        {
            "type": "Feature",
            "geometry": {
                "type": "Point",
                "coordinates": [
                    117.31,
                    24.7
                ]
            },
            "properties": {
                "type": "occurrence",
                "record": "<a href=https://www.gbif.org/occurrence/2417372170 target='_blank'>https://www.gbif.org/occurrence/2417372170</a>",
                "outlier": "false"
            }
        },
        {
            "type": "Feature",
            "geometry": {
                "type": "Point",
                "coordinates": [
                    107.11,
                    22.76
                ]
            },
            "properties": {
                "type": "occurrence",
                "record": "<a href=https://www.gbif.org/occurrence/2417436421 target='_blank'>https://www.gbif.org/occurrence/2417436421</a>",
                "outlier": "false"
            }
        },
        {
            "type": "Feature",
            "geometry": {
                "type": "Point",
                "coordinates": [
                    116.62,
                    24.33
                ]
            },
            "properties": {
                "type": "occurrence",
                "record": "<a href=https://www.gbif.org/occurrence/2417436564 target='_blank'>https://www.gbif.org/occurrence/2417436564</a>",
                "outlier": "false"
            }
        },
        {
            "type": "Feature",
            "geometry": {
                "type": "Point",
                "coordinates": [
                    116.62,
                    24.33
                ]
            },
            "properties": {
                "type": "occurrence",
                "record": "<a href=https://www.gbif.org/occurrence/2417439471 target='_blank'>https://www.gbif.org/occurrence/2417439471</a>",
                "outlier": "false"
            }
        },
        {
            "type": "Feature",
            "geometry": {
                "type": "Point",
                "coordinates": [
                    115.393921,
                    25.136922
                ]
            },
            "properties": {
                "type": "occurrence",
                "record": "<a href=https://www.gbif.org/occurrence/1030740723 target='_blank'>https://www.gbif.org/occurrence/1030740723</a>",
                "outlier": "false"
            }
        },
        {
            "type": "Feature",
            "geometry": {
                "type": "Point",
                "coordinates": [
                    110.585686,
                    25.60168
                ]
            },
            "properties": {
                "type": "occurrence",
                "record": "<a href=https://www.gbif.org/occurrence/1030984836 target='_blank'>https://www.gbif.org/occurrence/1030984836</a>",
                "outlier": "false"
            }
        },
        {
            "type": "Feature",
            "geometry": {
                "type": "Point",
                "coordinates": [
                    120.882778,
                    23.898056
                ]
            },
            "properties": {
                "type": "occurrence",
                "record": "<a href=https://www.gbif.org/occurrence/891690288 target='_blank'>https://www.gbif.org/occurrence/891690288</a>",
                "outlier": "false"
            }
        },
        {
            "type": "Feature",
            "geometry": {
                "type": "Point",
                "coordinates": [
                    120.882778,
                    23.898056
                ]
            },
            "properties": {
                "type": "occurrence",
                "record": "<a href=https://www.gbif.org/occurrence/891690327 target='_blank'>https://www.gbif.org/occurrence/891690327</a>",
                "outlier": "false"
            }
        },
        {
            "type": "Feature",
            "geometry": {
                "type": "Point",
                "coordinates": [
                    104.702829,
                    23.125462
                ]
            },
            "properties": {
                "type": "occurrence",
                "record": "<a href=https://www.gbif.org/occurrence/919553296 target='_blank'>https://www.gbif.org/occurrence/919553296</a>",
                "outlier": "false"
            }
        },
        {
            "type": "Feature",
            "geometry": {
                "type": "Point",
                "coordinates": [
                    104.702829,
                    23.125462
                ]
            },
            "properties": {
                "type": "occurrence",
                "record": "<a href=https://www.gbif.org/occurrence/919553308 target='_blank'>https://www.gbif.org/occurrence/919553308</a>",
                "outlier": "false"
            }
        },
        {
            "type": "Feature",
            "geometry": {
                "type": "Point",
                "coordinates": [
                    120.882778,
                    23.898056
                ]
            },
            "properties": {
                "type": "occurrence",
                "record": "<a href=https://www.gbif.org/occurrence/891588310 target='_blank'>https://www.gbif.org/occurrence/891588310</a>",
                "outlier": "false"
            }
        },
        {
            "type": "Feature",
            "geometry": {
                "type": "Point",
                "coordinates": [
                    119.149615,
                    26.191604
                ]
            },
            "properties": {
                "type": "occurrence",
                "record": "<a href=https://www.gbif.org/occurrence/1303855848 target='_blank'>https://www.gbif.org/occurrence/1303855848</a>",
                "outlier": "false"
            }
        },
        {
            "type": "Feature",
            "geometry": {
                "type": "Point",
                "coordinates": [
                    113.773813,
                    25.124499
                ]
            },
            "properties": {
                "type": "occurrence",
                "record": "<a href=https://www.gbif.org/occurrence/1303740311 target='_blank'>https://www.gbif.org/occurrence/1303740311</a>",
                "outlier": "false"
            }
        },
        {
            "type": "Feature",
            "geometry": {
                "type": "Point",
                "coordinates": [
                    114.639319,
                    23.03755
                ]
            },
            "properties": {
                "type": "occurrence",
                "record": "<a href=https://www.gbif.org/occurrence/1303856189 target='_blank'>https://www.gbif.org/occurrence/1303856189</a>",
                "outlier": "false"
            }
        },
        {
            "type": "Feature",
            "geometry": {
                "type": "Point",
                "coordinates": [
                    121.45,
                    24.85
                ]
            },
            "properties": {
                "type": "occurrence",
                "record": "<a href=https://www.gbif.org/occurrence/1821822199 target='_blank'>https://www.gbif.org/occurrence/1821822199</a>",
                "outlier": "false"
            }
        },
        {
            "type": "Feature",
            "geometry": {
                "type": "Point",
                "coordinates": [
                    121.45,
                    24.85
                ]
            },
            "properties": {
                "type": "occurrence",
                "record": "<a href=https://www.gbif.org/occurrence/1821822325 target='_blank'>https://www.gbif.org/occurrence/1821822325</a>",
                "outlier": "false"
            }
        },
        {
            "type": "Feature",
            "geometry": {
                "type": "Point",
                "coordinates": [
                    121.45,
                    24.85
                ]
            },
            "properties": {
                "type": "occurrence",
                "record": "<a href=https://www.gbif.org/occurrence/1821822333 target='_blank'>https://www.gbif.org/occurrence/1821822333</a>",
                "outlier": "false"
            }
        },
        {
            "type": "Feature",
            "geometry": {
                "type": "Point",
                "coordinates": [
                    116.625881,
                    24.33566
                ]
            },
            "properties": {
                "type": "occurrence",
                "record": "<a href=https://www.gbif.org/occurrence/1303740287 target='_blank'>https://www.gbif.org/occurrence/1303740287</a>",
                "outlier": "false"
            }
        },
        {
            "type": "Feature",
            "geometry": {
                "type": "Point",
                "coordinates": [
                    116.763457,
                    25.707879
                ]
            },
            "properties": {
                "type": "occurrence",
                "record": "<a href=https://www.gbif.org/occurrence/1303740324 target='_blank'>https://www.gbif.org/occurrence/1303740324</a>",
                "outlier": "false"
            }
        },
        {
            "type": "Feature",
            "geometry": {
                "type": "Point",
                "coordinates": [
                    116.625881,
                    24.33566
                ]
            },
            "properties": {
                "type": "occurrence",
                "record": "<a href=https://www.gbif.org/occurrence/1303856028 target='_blank'>https://www.gbif.org/occurrence/1303856028</a>",
                "outlier": "false"
            }
        },
        {
            "type": "Feature",
            "geometry": {
                "type": "Point",
                "coordinates": [
                    116.94221,
                    23.869209
                ]
            },
            "properties": {
                "type": "occurrence",
                "record": "<a href=https://www.gbif.org/occurrence/1030984809 target='_blank'>https://www.gbif.org/occurrence/1030984809</a>",
                "outlier": "false"
            }
        },
        {
            "type": "Feature",
            "geometry": {
                "type": "Point",
                "coordinates": [
                    113.604544,
                    24.682731
                ]
            },
            "properties": {
                "type": "occurrence",
                "record": "<a href=https://www.gbif.org/occurrence/1030984824 target='_blank'>https://www.gbif.org/occurrence/1030984824</a>",
                "outlier": "false"
            }
        },
        {
            "type": "Feature",
            "geometry": {
                "type": "Point",
                "coordinates": [
                    116.94221,
                    23.869209
                ]
            },
            "properties": {
                "type": "occurrence",
                "record": "<a href=https://www.gbif.org/occurrence/1303643413 target='_blank'>https://www.gbif.org/occurrence/1303643413</a>",
                "outlier": "false"
            }
        },
        {
            "type": "Feature",
            "geometry": {
                "type": "Point",
                "coordinates": [
                    113.604544,
                    24.682731
                ]
            },
            "properties": {
                "type": "occurrence",
                "record": "<a href=https://www.gbif.org/occurrence/1303855793 target='_blank'>https://www.gbif.org/occurrence/1303855793</a>",
                "outlier": "false"
            }
        },
        {
            "type": "Feature",
            "geometry": {
                "type": "Point",
                "coordinates": [
                    113.604544,
                    24.682731
                ]
            },
            "properties": {
                "type": "occurrence",
                "record": "<a href=https://www.gbif.org/occurrence/1303855810 target='_blank'>https://www.gbif.org/occurrence/1303855810</a>",
                "outlier": "false"
            }
        },
        {
            "type": "Feature",
            "geometry": {
                "type": "Point",
                "coordinates": [
                    113.604544,
                    24.682731
                ]
            },
            "properties": {
                "type": "occurrence",
                "record": "<a href=https://www.gbif.org/occurrence/1303855827 target='_blank'>https://www.gbif.org/occurrence/1303855827</a>",
                "outlier": "false"
            }
        },
        {
            "type": "Feature",
            "geometry": {
                "type": "Point",
                "coordinates": [
                    113.604544,
                    24.682731
                ]
            },
            "properties": {
                "type": "occurrence",
                "record": "<a href=https://www.gbif.org/occurrence/1303855837 target='_blank'>https://www.gbif.org/occurrence/1303855837</a>",
                "outlier": "false"
            }
        },
        {
            "type": "Feature",
            "geometry": {
                "type": "Point",
                "coordinates": [
                    113.604544,
                    24.682731
                ]
            },
            "properties": {
                "type": "occurrence",
                "record": "<a href=https://www.gbif.org/occurrence/1303855849 target='_blank'>https://www.gbif.org/occurrence/1303855849</a>",
                "outlier": "false"
            }
        },
        {
            "type": "Feature",
            "geometry": {
                "type": "Point",
                "coordinates": [
                    113.604544,
                    24.682731
                ]
            },
            "properties": {
                "type": "occurrence",
                "record": "<a href=https://www.gbif.org/occurrence/1303855924 target='_blank'>https://www.gbif.org/occurrence/1303855924</a>",
                "outlier": "false"
            }
        },
        {
            "type": "Feature",
            "geometry": {
                "type": "Point",
                "coordinates": [
                    113.604544,
                    24.682731
                ]
            },
            "properties": {
                "type": "occurrence",
                "record": "<a href=https://www.gbif.org/occurrence/1303856000 target='_blank'>https://www.gbif.org/occurrence/1303856000</a>",
                "outlier": "false"
            }
        },
        {
            "type": "Feature",
            "geometry": {
                "type": "Point",
                "coordinates": [
                    113.604544,
                    24.682731
                ]
            },
            "properties": {
                "type": "occurrence",
                "record": "<a href=https://www.gbif.org/occurrence/1303856002 target='_blank'>https://www.gbif.org/occurrence/1303856002</a>",
                "outlier": "false"
            }
        },
        {
            "type": "Feature",
            "geometry": {
                "type": "Point",
                "coordinates": [
                    113.604544,
                    24.682731
                ]
            },
            "properties": {
                "type": "occurrence",
                "record": "<a href=https://www.gbif.org/occurrence/1303856052 target='_blank'>https://www.gbif.org/occurrence/1303856052</a>",
                "outlier": "false"
            }
        },
        {
            "type": "Feature",
            "geometry": {
                "type": "Point",
                "coordinates": [
                    118.698285,
                    25.440455
                ]
            },
            "properties": {
                "type": "occurrence",
                "record": "<a href=https://www.gbif.org/occurrence/1303740292 target='_blank'>https://www.gbif.org/occurrence/1303740292</a>",
                "outlier": "false"
            }
        },
        {
            "type": "Feature",
            "geometry": {
                "type": "Point",
                "coordinates": [
                    115.259746,
                    24.100164
                ]
            },
            "properties": {
                "type": "occurrence",
                "record": "<a href=https://www.gbif.org/occurrence/1303855971 target='_blank'>https://www.gbif.org/occurrence/1303855971</a>",
                "outlier": "false"
            }
        },
        {
            "type": "Feature",
            "geometry": {
                "type": "Point",
                "coordinates": [
                    109.66639,
                    19.02583
                ]
            },
            "properties": {
                "type": "occurrence",
                "record": "<a href=https://www.gbif.org/occurrence/731010261 target='_blank'>https://www.gbif.org/occurrence/731010261</a>",
                "outlier": "false"
            }
        },
        {
            "type": "Feature",
            "geometry": {
                "type": "Point",
                "coordinates": [
                    120.915278,
                    23.875
                ]
            },
            "properties": {
                "type": "occurrence",
                "record": "<a href=https://www.gbif.org/occurrence/891690778 target='_blank'>https://www.gbif.org/occurrence/891690778</a>",
                "outlier": "false"
            }
        },
        {
            "type": "Feature",
            "geometry": {
                "type": "Point",
                "coordinates": [
                    120.915278,
                    23.875
                ]
            },
            "properties": {
                "type": "occurrence",
                "record": "<a href=https://www.gbif.org/occurrence/891690789 target='_blank'>https://www.gbif.org/occurrence/891690789</a>",
                "outlier": "false"
            }
        },
        {
            "type": "Feature",
            "geometry": {
                "type": "Point",
                "coordinates": [
                    121.251667,
                    23.972778
                ]
            },
            "properties": {
                "type": "occurrence",
                "record": "<a href=https://www.gbif.org/occurrence/1821801191 target='_blank'>https://www.gbif.org/occurrence/1821801191</a>",
                "outlier": "false"
            }
        },
        {
            "type": "Feature",
            "geometry": {
                "type": "Point",
                "coordinates": [
                    121.251667,
                    23.972778
                ]
            },
            "properties": {
                "type": "occurrence",
                "record": "<a href=https://www.gbif.org/occurrence/1821800779 target='_blank'>https://www.gbif.org/occurrence/1821800779</a>",
                "outlier": "false"
            }
        },
        {
            "type": "Feature",
            "geometry": {
                "type": "Point",
                "coordinates": [
                    120.871667,
                    22.195278
                ]
            },
            "properties": {
                "type": "occurrence",
                "record": "<a href=https://www.gbif.org/occurrence/891690810 target='_blank'>https://www.gbif.org/occurrence/891690810</a>",
                "outlier": "false"
            }
        },
        {
            "type": "Feature",
            "geometry": {
                "type": "Point",
                "coordinates": [
                    121.016111,
                    23.966667
                ]
            },
            "properties": {
                "type": "occurrence",
                "record": "<a href=https://www.gbif.org/occurrence/1821838337 target='_blank'>https://www.gbif.org/occurrence/1821838337</a>",
                "outlier": "false"
            }
        },
        {
            "type": "Feature",
            "geometry": {
                "type": "Point",
                "coordinates": [
                    121.966667,
                    23.966667
                ]
            },
            "properties": {
                "type": "occurrence",
                "record": "<a href=https://www.gbif.org/occurrence/2825644306 target='_blank'>https://www.gbif.org/occurrence/2825644306</a>",
                "outlier": "false"
            }
        },
        {
            "type": "Feature",
            "geometry": {
                "type": "Point",
                "coordinates": [
                    121.966667,
                    23.966667
                ]
            },
            "properties": {
                "type": "occurrence",
                "record": "<a href=https://www.gbif.org/occurrence/2825648312 target='_blank'>https://www.gbif.org/occurrence/2825648312</a>",
                "outlier": "false"
            }
        },
        {
            "type": "Feature",
            "geometry": {
                "type": "Point",
                "coordinates": [
                    120.862778,
                    22.089722
                ]
            },
            "properties": {
                "type": "occurrence",
                "record": "<a href=https://www.gbif.org/occurrence/891650725 target='_blank'>https://www.gbif.org/occurrence/891650725</a>",
                "outlier": "false"
            }
        },
        {
            "type": "Feature",
            "geometry": {
                "type": "Point",
                "coordinates": [
                    120.769167,
                    23.5275
                ]
            },
            "properties": {
                "type": "occurrence",
                "record": "<a href=https://www.gbif.org/occurrence/1821790916 target='_blank'>https://www.gbif.org/occurrence/1821790916</a>",
                "outlier": "false"
            }
        },
        {
            "type": "Feature",
            "geometry": {
                "type": "Point",
                "coordinates": [
                    120.671111,
                    24.1375
                ]
            },
            "properties": {
                "type": "occurrence",
                "record": "<a href=https://www.gbif.org/occurrence/1821790982 target='_blank'>https://www.gbif.org/occurrence/1821790982</a>",
                "outlier": "false"
            }
        },
        {
            "type": "Feature",
            "geometry": {
                "type": "Point",
                "coordinates": [
                    120.964167,
                    23.729444
                ]
            },
            "properties": {
                "type": "occurrence",
                "record": "<a href=https://www.gbif.org/occurrence/1821790896 target='_blank'>https://www.gbif.org/occurrence/1821790896</a>",
                "outlier": "false"
            }
        },
        {
            "type": "Feature",
            "geometry": {
                "type": "Point",
                "coordinates": [
                    120.681389,
                    23.900556
                ]
            },
            "properties": {
                "type": "occurrence",
                "record": "<a href=https://www.gbif.org/occurrence/1821790973 target='_blank'>https://www.gbif.org/occurrence/1821790973</a>",
                "outlier": "false"
            }
        },
        {
            "type": "Feature",
            "geometry": {
                "type": "Point",
                "coordinates": [
                    120.882778,
                    23.898056
                ]
            },
            "properties": {
                "type": "occurrence",
                "record": "<a href=https://www.gbif.org/occurrence/891650620 target='_blank'>https://www.gbif.org/occurrence/891650620</a>",
                "outlier": "false"
            }
        },
        {
            "type": "Feature",
            "geometry": {
                "type": "Point",
                "coordinates": [
                    120.882778,
                    23.898056
                ]
            },
            "properties": {
                "type": "occurrence",
                "record": "<a href=https://www.gbif.org/occurrence/891650627 target='_blank'>https://www.gbif.org/occurrence/891650627</a>",
                "outlier": "false"
            }
        },
        {
            "type": "Feature",
            "geometry": {
                "type": "Point",
                "coordinates": [
                    120.882778,
                    23.898056
                ]
            },
            "properties": {
                "type": "occurrence",
                "record": "<a href=https://www.gbif.org/occurrence/891650685 target='_blank'>https://www.gbif.org/occurrence/891650685</a>",
                "outlier": "false"
            }
        },
        {
            "type": "Feature",
            "geometry": {
                "type": "Point",
                "coordinates": [
                    120.959444,
                    23.961389
                ]
            },
            "properties": {
                "type": "occurrence",
                "record": "<a href=https://www.gbif.org/occurrence/891650695 target='_blank'>https://www.gbif.org/occurrence/891650695</a>",
                "outlier": "false"
            }
        },
        {
            "type": "Feature",
            "geometry": {
                "type": "Point",
                "coordinates": [
                    120.959444,
                    23.961389
                ]
            },
            "properties": {
                "type": "occurrence",
                "record": "<a href=https://www.gbif.org/occurrence/891690402 target='_blank'>https://www.gbif.org/occurrence/891690402</a>",
                "outlier": "false"
            }
        },
        {
            "type": "Feature",
            "geometry": {
                "type": "MultiPolygon",
                "coordinates": [
                    [
                        [
                            [
                                109.66639,
                                19.02583
                            ],
                            [
                                108.796035,
                                19.52403
                            ],
                            [
                                109.119056,
                                19.821039
                            ],
                            [
                                110.211599,
                                20.101254
                            ],
                            [
                                110.786551,
                                20.077534
                            ],
                            [
                                111.010051,
                                19.69593
                            ],
                            [
                                110.589068,
                                19.274327
                            ],
                            [
                                109.66639,
                                19.02583
                            ]
                        ]
                    ],
                    [
                        [
                            [
                                106.730161,
                                20.706558
                            ],
                            [
                                103.086573,
                                22.792186
                            ],
                            [
                                105.055261,
                                24.046484
                            ],
                            [
                                107.54,
                                25.59
                            ],
                            [
                                108.45,
                                26.0
                            ],
                            [
                                120.17,
                                30.27
                            ],
                            [
                                120.881518,
                                27.773747
                            ],
                            [
                                120.395508,
                                27.053284
                            ],
                            [
                                119.58551,
                                25.740906
                            ],
                            [
                                118.656921,
                                24.547485
                            ],
                            [
                                117.281677,
                                23.624512
                            ],
                            [
                                115.890686,
                                22.782898
                            ],
                            [
                                114.763916,
                                22.668091
                            ],
                            [
                                114.152527,
                                22.223877
                            ],
                            [
                                113.806885,
                                22.548279
                            ],
                            [
                                113.241089,
                                22.051514
                            ],
                            [
                                111.843689,
                                21.550476
                            ],
                            [
                                110.785522,
                                21.397278
                            ],
                            [
                                110.444092,
                                20.341125
                            ],
                            [
                                109.889893,
                                20.282471
                            ],
                            [
                                109.627686,
                                21.008301
                            ],
                            [
                                109.864502,
                                21.395081
                            ],
                            [
                                108.522888,
                                21.715271
                            ],
                            [
                                108.050293,
                                21.55249
                            ],
                            [
                                106.730161,
                                20.706558
                            ]
                        ]
                    ],
                    [
                        [
                            [
                                121.609151,
                                25.220956
                            ],
                            [
                                121.811442,
                                24.511249
                            ],
                            [
                                121.777818,
                                24.394274
                            ],
                            [
                                121.175632,
                                22.790857
                            ],
                            [
                                120.771115,
                                22.016576
                            ],
                            [
                                120.725956,
                                22.004414
                            ],
                            [
                                120.220083,
                                22.814861
                            ],
                            [
                                120.106189,
                                23.556263
                            ],
                            [
                                120.69468,
                                24.538451
                            ],
                            [
                                121.495044,
                                25.295459
                            ],
                            [
                                121.609151,
                                25.220956
                            ]
                        ]
                    ]
                ]
            },
            "properties": {
                "type": "geographic_range"
            }
        }
    ]
}